littlechat/__init__.py
littlechat/cli.py
littlechat/client.py
littlechat/server.py
littlechat/front/__init__.py
littlechat/front/front_button.py
littlechat/front/front_config.py
littlechat/front/front_edit.py
littlechat/front/front_emojis.py
littlechat/front/front_msg.py
littlechat/front/front_text.py
littlechat/front/front_text_canvas.py
littlechat/front/front_text_layout.py
littlechat/front/main_page.py
littlechat/stuff/__init__.py
littlechat/stuff/config.py
littlechat/stuff/errors.py
littlechat/stuff/msg_boxes.py
littlechat/utils/__init__.py
littlechat/utils/util_log.py
littlechat/utils/util_path.py
littlechat/utils/util_thread.py
littlechat-0.0.7.data/data/requirements/requirements.txt
littlechat-0.0.7.dist-info/LICENSE
littlechat-0.0.7.dist-info/METADATA
littlechat-0.0.7.dist-info/WHEEL
littlechat-0.0.7.dist-info/entry_points.txt
littlechat-0.0.7.dist-info/top_level.txt
littlechat-0.0.7.dist-info/RECORD
