Metadata-Version: 2.1
Name: littlechat
Version: 0.0.7
Summary: A little chatroom run in console base on `urwid` and `UDP`, only support Linux, OSX, Cygwin or other unix-like OS
Home-page: https://github.com/yujun2647/littlechat
Download-URL: 
Author: walkerjun
Author-email: yujun2647@163.com
License: Apache-2.0
Requires-Python: >=3.7
License-File: LICENSE
Requires-Dist: urwid
